keepit/VERSION
keepit/__init__.py
keepit/version.py
keepit/__pycache__/__init__.cpython-37.pyc
keepit/backends/__init__.py
keepit/backends/pickle.py
keepit/backends/__pycache__/__init__.cpython-37.pyc
keepit-0.2.2.dist-info/LICENSE.txt
keepit-0.2.2.dist-info/METADATA
keepit-0.2.2.dist-info/WHEEL
keepit-0.2.2.dist-info/entry_points.txt
keepit-0.2.2.dist-info/top_level.txt
keepit-0.2.2.dist-info/RECORD
